vEMden/__init__.py
vEMden/vEMden.py
vEMden-0.2.dist-info/METADATA
vEMden-0.2.dist-info/WHEEL
vEMden-0.2.dist-info/entry_points.txt
vEMden-0.2.dist-info/top_level.txt
vEMden-0.2.dist-info/RECORD
